subtitle_generator.py
fcpxml_subtitle_generator-0.1.1.dist-info/licenses/LICENSE
fcpxml_subtitle_generator-0.1.1.dist-info/METADATA
fcpxml_subtitle_generator-0.1.1.dist-info/WHEEL
fcpxml_subtitle_generator-0.1.1.dist-info/entry_points.txt
fcpxml_subtitle_generator-0.1.1.dist-info/top_level.txt
fcpxml_subtitle_generator-0.1.1.dist-info/RECORD
