Metadata-Version: 2.4
Name: fcpxml-subtitle-generator
Version: 0.1.1
Summary: CLI tool to generate Final Cut Pro compatible subtitle files from audio/video files using Whisper
Author-email: taejun0622 <taejun0622@gmail.com>
License-Expression: MIT
Project-URL: Homepage, https://github.com/taejun0622/fcpxml-subtitle-generator
Project-URL: Repository, https://github.com/taejun0622/fcpxml-subtitle-generator
Project-URL: Issues, https://github.com/taejun0622/fcpxml-subtitle-generator/issues
Keywords: subtitle,whisper,final-cut-pro,transcription,video,audio
Classifier: Development Status :: 4 - Beta
Classifier: Intended Audience :: Developers
Classifier: Intended Audience :: End Users/Desktop
Classifier: Programming Language :: Python :: 3
Classifier: Programming Language :: Python :: 3.13
Classifier: Topic :: Multimedia :: Video
Classifier: Topic :: Multimedia :: Sound/Audio :: Speech
Classifier: Topic :: Software Development :: Libraries :: Python Modules
Classifier: Operating System :: OS Independent
Requires-Python: >=3.13
License-File: LICENSE
Requires-Dist: moviepy>=2.2.1
Requires-Dist: openai-whisper>=20250625
Dynamic: license-file
